openodia/__init__.py
openodia/__main__.py
openodia/_letters.py
openodia/_odianames.py
openodia/_summarization.py
openodia/_translate.py
openodia/_understandData.py
openodia/common/__init__.py
openodia/common/constants.py
openodia/common/utility.py
openodia/corpus/En-Or_word_pairs_v3.json
openodia/corpus/__init__.py
openodia/corpus/dictionary.py
openodia/corpus/embeddings.txt
openodia-0.1.12.dist-info/METADATA
openodia-0.1.12.dist-info/WHEEL
openodia-0.1.12.dist-info/licenses/LICENSE
openodia-0.1.12.dist-info/RECORD
