Metadata-Version: 2.4
Name: openodia
Version: 0.1.12
Summary: Open source Odia language tools
Project-URL: Repository, https://github.com/soumendrak/openodia
Project-URL: Documentation, https://openodia.soumendrak.com
Project-URL: Issues, https://github.com/soumendrak/openodia/issues
Author-email: Soumendra Kumar Sahoo <proud_odia@outlook.com>
License: MIT
License-File: LICENSE
Keywords: github-actions,nlp,odia,packaging,pip,pypi,python,uv
Classifier: Development Status :: 4 - Beta
Classifier: Intended Audience :: Developers
Classifier: License :: OSI Approved :: MIT License
Classifier: Programming Language :: Python :: 3
Classifier: Programming Language :: Python :: 3.9
Classifier: Programming Language :: Python :: 3.10
Classifier: Programming Language :: Python :: 3.11
Classifier: Programming Language :: Python :: 3.12
Classifier: Programming Language :: Python :: 3.13
Classifier: Topic :: Software Development :: Libraries :: Python Modules
Classifier: Topic :: Text Processing :: Linguistic
Requires-Python: >=3.9
Requires-Dist: deep-translator>=1.11.4
Requires-Dist: faker>=13.4.0
Requires-Dist: numpy>=1.22.3
Requires-Dist: rich>=12.2.0
Provides-Extra: dev
Requires-Dist: bandit>=1.7.1; extra == 'dev'
Requires-Dist: commitizen>=2.27.1; extra == 'dev'
Requires-Dist: mkdocs-git-revision-date-localized-plugin>=0.10.0; extra == 'dev'
Requires-Dist: mkdocs-material>=7.3.2; extra == 'dev'
Requires-Dist: mkdocs>=1.2.2; extra == 'dev'
Requires-Dist: pre-commit>=2.17.0; extra == 'dev'
Requires-Dist: pytest-cov>=3.0.0; extra == 'dev'
Requires-Dist: pytest>=6.2.5; extra == 'dev'
Requires-Dist: ruff>=0.1.0; extra == 'dev'
